rdlocrand/__init__.py
rdlocrand/rdlocrand_fun.py
rdlocrand/rdrandinf.py
rdlocrand/rdrbounds.py
rdlocrand/rdsensitivity.py
rdlocrand/rdwinselect.py
rdlocrand-1.0.5.dist-info/METADATA
rdlocrand-1.0.5.dist-info/WHEEL
rdlocrand-1.0.5.dist-info/top_level.txt
rdlocrand-1.0.5.dist-info/RECORD
