Metadata-Version: 2.1
Name: rdlocrand
Version: 1.0.5
Summary: Local Randomization Methods for RD Designs
Home-page: https://rdpackages.github.io/rdlocrand/
Author: Matias D. Cattaneo, Ricardo Masini
Author-email: cattaneo@princeton.edu
Project-URL: Bug Tracker, https://github.com/rdpackages/rdlocrand/issues
Classifier: Programming Language :: Python :: 3
Classifier: License :: OSI Approved :: MIT License
Classifier: Operating System :: OS Independent
Requires-Python: >=3.8
Requires-Dist: numpy>=2.1.0
Requires-Dist: pandas>=2.2.0
Requires-Dist: scipy>=1.12.0
Requires-Dist: statsmodels>=0.14.1
Requires-Dist: linearmodels>=5.4
